image_collector/__init__.py
image_collector/image_collector.py
image_collector-0.0.5.dist-info/LICENSE
image_collector-0.0.5.dist-info/METADATA
image_collector-0.0.5.dist-info/WHEEL
image_collector-0.0.5.dist-info/entry_points.txt
image_collector-0.0.5.dist-info/top_level.txt
image_collector-0.0.5.dist-info/RECORD
