Metadata-Version: 2.1
Name: image-collector
Version: 0.0.5
Summary: 简易图片采集工具,直接命令行运行就可以了，很简单～。版本[0.0.5]更新内容：提供命令行接口
Home-page: https://github.com/Deali-Axy
Author: DealiAxy
Author-email: dealiaxy@gmail.com
License: UNKNOWN
Platform: UNKNOWN
Classifier: Programming Language :: Python :: 3.6
Classifier: License :: OSI Approved :: GNU General Public License v3 (GPLv3)
Classifier: Operating System :: OS Independent
Requires-Dist: requests
